lifespline_utils/config.py
lifespline_utils/error.py
lifespline_utils/example.py
lifespline_utils/log.py
lifespline_utils/utils.py
lifespline_utils-0.0.8.dist-info/LICENSE.md
lifespline_utils-0.0.8.dist-info/METADATA
lifespline_utils-0.0.8.dist-info/WHEEL
lifespline_utils-0.0.8.dist-info/top_level.txt
lifespline_utils-0.0.8.dist-info/RECORD
